{
  "snapshot_sha": "19585c4cb28ebdda84190a36d6b916b7b77c9588",
  "head_sha": "bccbab60da3962553390d4015c351a01d065720c",
  "window_days": 365,
  "n_functions": 936,
  "n_change_prone": 15,
  "n_future_commits": 127,
  "insufficient_past_history": false,
  "functions": [
    {
      "target": "pygments/cmdline.py::main_inner",
      "future_commits": 1,
      "future_lines": 1,
      "past_commits": 0,
      "past_lines": 0,
      "change_prone": true
    },
    {
      "target": "pygments/formatters/html.py::HtmlFormatter.__init__",
      "future_commits": 5,
      "future_lines": 31,
      "past_commits": 0,
      "past_lines": 0,
      "change_prone": true
    },
    {
      "target": "pygments/formatters/html.py::HtmlFormatter._translate_parts",
      "future_commits": 1,
      "future_lines": 1,
      "past_commits": 0,
      "past_lines": 0,
      "change_prone": true
    },
    {
      "target": "pygments/formatters/html.py::webify",
      "future_commits": 0,
      "future_lines": 0,
      "past_commits": 1,
      "past_lines": 9,
      "change_prone": false
    },
    {
      "target": "pygments/formatters/img.py::FontManager._create_mac",
      "future_commits": 0,
      "future_lines": 0,
      "past_commits": 1,
      "past_lines": 2,
      "change_prone": false
    },
    {
      "target": "pygments/formatters/svg.py::SvgFormatter.format_unencoded",
      "future_commits": 1,
      "future_lines": 1,
      "past_commits": 0,
      "past_lines": 0,
      "change_prone": true
    },
    {
      "target": "pygments/formatters/terminal256.py::Terminal256Formatter._build_color_table",
      "future_commits": 1,
      "future_lines": 4,
      "past_commits": 0,
      "past_lines": 0,
      "change_prone": true
    },
    {
      "target": "pygments/formatters/terminal256.py::Terminal256Formatter._closest_color",
      "future_commits": 1,
      "future_lines": 1,
      "past_commits": 0,
      "past_lines": 0,
      "change_prone": true
    },
    {
      "target": "pygments/lexer.py::using",
      "future_commits": 1,
      "future_lines": 6,
      "past_commits": 0,
      "past_lines": 0,
      "change_prone": true
    },
    {
      "target": "pygments/lexer.py::using.callback",
      "future_commits": 1,
      "future_lines": 6,
      "past_commits": 0,
      "past_lines": 0,
      "change_prone": true
    },
    {
      "target": "pygments/lexers/_php_builtins.py::get_php_references",
      "future_commits": 1,
      "future_lines": 3,
      "past_commits": 0,
      "past_lines": 0,
      "change_prone": true
    },
    {
      "target": "pygments/lexers/_php_builtins.py::run",
      "future_commits": 1,
      "future_lines": 1,
      "past_commits": 0,
      "past_lines": 0,
      "change_prone": true
    },
    {
      "target": "pygments/lexers/actionscript.py::ActionScript3Lexer.analyse_text",
      "future_commits": 1,
      "future_lines": 2,
      "past_commits": 0,
      "past_lines": 0,
      "change_prone": true
    },
    {
      "target": "pygments/lexers/haxe.py::HaxeLexer.analyse_text",
      "future_commits": 1,
      "future_lines": 8,
      "past_commits": 0,
      "past_lines": 0,
      "change_prone": true
    },
    {
      "target": "pygments/lexers/json5.py::quoted_field_name",
      "future_commits": 0,
      "future_lines": 0,
      "past_commits": 2,
      "past_lines": 17,
      "change_prone": false
    },
    {
      "target": "pygments/lexers/json5.py::string_rules",
      "future_commits": 0,
      "future_lines": 0,
      "past_commits": 2,
      "past_lines": 17,
      "change_prone": false
    },
    {
      "target": "pygments/lexers/maple.py::MapleLexer.analyse_text",
      "future_commits": 0,
      "future_lines": 0,
      "past_commits": 1,
      "past_lines": 4,
      "change_prone": false
    },
    {
      "target": "pygments/lexers/maple.py::MapleLexer.delayed_callback",
      "future_commits": 0,
      "future_lines": 0,
      "past_commits": 1,
      "past_lines": 14,
      "change_prone": false
    },
    {
      "target": "pygments/lexers/mojo.py::MojoLexer.analyse_text",
      "future_commits": 0,
      "future_lines": 0,
      "past_commits": 1,
      "past_lines": 6,
      "change_prone": false
    },
    {
      "target": "pygments/lexers/oberon.py::ComponentPascalLexer.analyse_text",
      "future_commits": 1,
      "future_lines": 1,
      "past_commits": 0,
      "past_lines": 0,
      "change_prone": true
    },
    {
      "target": "pygments/lexers/scripting.py::LuaLexer.get_tokens_unprocessed",
      "future_commits": 0,
      "future_lines": 0,
      "past_commits": 1,
      "past_lines": 4,
      "change_prone": false
    },
    {
      "target": "pygments/lexers/scripting.py::_luau_make_expression",
      "future_commits": 1,
      "future_lines": 2,
      "past_commits": 0,
      "past_lines": 0,
      "change_prone": true
    },
    {
      "target": "pygments/lexers/scripting.py::all_lua_builtins",
      "future_commits": 0,
      "future_lines": 0,
      "past_commits": 1,
      "past_lines": 4,
      "change_prone": false
    },
    {
      "target": "pygments/lexers/sql.py::GoogleSqlLexer.analyse_text",
      "future_commits": 0,
      "future_lines": 0,
      "past_commits": 3,
      "past_lines": 167,
      "change_prone": false
    },
    {
      "target": "pygments/lexers/typst.py::TypstLexer.__init__",
      "future_commits": 0,
      "future_lines": 0,
      "past_commits": 1,
      "past_lines": 13,
      "change_prone": false
    },
    {
      "target": "pygments/lexers/typst.py::TypstLexer.get_tokens_unprocessed",
      "future_commits": 0,
      "future_lines": 0,
      "past_commits": 1,
      "past_lines": 13,
      "change_prone": false
    },
    {
      "target": "pygments/util.py::guess_decode",
      "future_commits": 1,
      "future_lines": 1,
      "past_commits": 0,
      "past_lines": 0,
      "change_prone": true
    }
  ]
}
